fressnapftracker/__init__.py
fressnapftracker/exceptions.py
fressnapftracker/fressnapftracker.py
fressnapftracker/models.py
fressnapftracker-0.2.1.dist-info/METADATA
fressnapftracker-0.2.1.dist-info/WHEEL
fressnapftracker-0.2.1.dist-info/licenses/LICENSE
fressnapftracker-0.2.1.dist-info/RECORD
