Metadata-Version: 2.4
Name: fressnapftracker
Version: 0.2.1
Summary: Asynchronous Python client for the Fressnapf Tracker GPS API
Project-URL: repository, https://github.com/eifinger/fressnapftracker
Author-email: Kevin Stillhammer <kevin.stillhammer@gmail.com>
License-Expression: Apache-2.0
License-File: LICENSE
Keywords: asyncio,fressnapf,gps,httpx,pet-tracker,tracker
Classifier: Intended Audience :: Developers
Classifier: Operating System :: OS Independent
Classifier: Programming Language :: Python
Classifier: Programming Language :: Python :: 3
Classifier: Programming Language :: Python :: 3.13
Classifier: Topic :: Software Development :: Libraries :: Python Modules
Requires-Python: >=3.13
Requires-Dist: httpx>=0.28.0
Requires-Dist: pydantic>=2.10.0
